dr_files/__init__.py
dr_files/pb/__init__.py
dr_files/pb/build.sh
dr_files/pb/headers.proto
dr_files/pb/headers_pb2.py
dr_files/tests.py
dr_files/utilities.py
dr_files-0.1.5.dist-info/WHEEL
dr_files-0.1.5.dist-info/METADATA
dr_files-0.1.5.dist-info/RECORD
